<?xml version="1.0" encoding="UTF-8"?>
<minimalist xmlns="https://github.com/SSMetadataSummer2017/MetadataProjectSarah-Sam"
    xmlns:xsi="http://www.w3.org/2001/XMLSchema-instance"
    xmlns:dc="http://purl.org/dc/elements/1.1/" xmlns:dcterms="http://purl.org/dc/terms/"
    xmlns:mods="http://www.loc.gov/mods/v3" xmlns:vra="http://www.vraweb.org/vracore4.htm"
    xmlns:cdwalite="http://www.getty.edu/CDWA/CDWALite"
    xsi:schemaLocation="https://github.com/SSMetadataSummer2017/MetadataProjectSarah-Sam https://raw.githubusercontent.com/SSMetadataSummer2017/MetadataProjectSarah-Sam/master/minimalist_schema.xsd">
    
    <cdwaLiteSection>
        <cdwalite:cdwalite>
            <cdwalite:descriptiveMetadata>
                <cdwalite:objectWorkTypeWrap>
                    <cdwalite:objectWorkType>Sculpture</cdwalite:objectWorkType>
                </cdwalite:objectWorkTypeWrap>
                <cdwalite:titleWrap>
                    <cdwalite:titleSet>
                        <cdwalite:title>Bette and the Giant Jewfish</cdwalite:title>
                    </cdwalite:titleSet>
                </cdwalite:titleWrap>
                <cdwalite:displayCreator>Larry Bell, American , 1939–Present, Chicago, Illinois</cdwalite:displayCreator>
                <cdwalite:indexingCreatorWrap>
                    <cdwalite:indexingCreatorSet>
                        <cdwalite:nameCreatorSet>
                            <cdwalite:nameCreator>Bell, Larry</cdwalite:nameCreator>
                        </cdwalite:nameCreatorSet>
                        <cdwalite:roleCreator>artist</cdwalite:roleCreator>
                    </cdwalite:indexingCreatorSet>
                </cdwalite:indexingCreatorWrap>
                <cdwalite:displayMaterialsTech>Vacuum-coated glass, chrome-plated metal</cdwalite:displayMaterialsTech>
                <cdwalite:displayCreationDate>1963</cdwalite:displayCreationDate>
                <cdwalite:indexingDatesWrap>
                    <cdwalite:indexingDatesSet>
                        <cdwalite:earliestDate>1939</cdwalite:earliestDate>
                        <cdwalite:latestDate>Present</cdwalite:latestDate>
                    </cdwalite:indexingDatesSet>
                </cdwalite:indexingDatesWrap>
                <cdwalite:locationWrap>
                    <cdwalite:locationSet>
                        <cdwalite:locationName>Laguna Art Museum (Long Beach,Ca)</cdwalite:locationName>
                    </cdwalite:locationSet>
                </cdwalite:locationWrap>
            </cdwalite:descriptiveMetadata>
            <cdwalite:administrativeMetadata>
                <cdwalite:rightsWork>©2017 Laguna Art Museum All Rights Reserved</cdwalite:rightsWork>
            </cdwalite:administrativeMetadata>
        </cdwalite:cdwalite>
    </cdwaLiteSection>
    
    <vraSection>
        <vra:work>
            <vra:culturalContextSet>
                <vra:culturalContext>American</vra:culturalContext>
            </vra:culturalContextSet>
            <vra:locationSet>
                <vra:display>Laguna Art Museum</vra:display>
                <vra:location type="repository"> </vra:location>
            </vra:locationSet>
            <vra:measurementsSet>
                <vra:display>36 x 36 x 36 in.</vra:display>
                <vra:measurements type="height" unit="m">36</vra:measurements>
                <vra:measurements type="width" unit="m">36</vra:measurements>
            </vra:measurementsSet>
            <vra:sourceSet>
                <vra:display>Core 4 Sample Database (VCat)</vra:display>
                <vra:source>
                    <vra:name>Core 4 Sample Database (VCat)</vra:name>
                </vra:source>
            </vra:sourceSet>
            <vra:stylePeriodSet>
                <vra:display>Minimalist; Twentieth century</vra:display>
                <vra:stylePeriod vocab="LCSAF" refid="sh 85091984">Twentieth century</vra:stylePeriod>
                <vra:stylePeriod vocab="AAT" refid="300021269">Minimalist</vra:stylePeriod>
            </vra:stylePeriodSet>
            <vra:subjectSet>
                <vra:display>Minimalist art</vra:display>
                <vra:notes/>
                <vra:subject>
                    <vra:term type="personalName" vocab="LCNAF" refid="n 79054933">Bell, Larry</vra:term>
                </vra:subject>
            </vra:subjectSet>
            <vra:worktypeSet>
                <vra:display>sculptures (visual works)</vra:display>
                <vra:worktype vocab="AAT" refid="300033799">sculptures (visual work)</vra:worktype>
            </vra:worktypeSet>
        </vra:work>
      <image id="i_143"
        href="http://www.core.vraweb.org/examples/html/example047_full.html"
        refid="143" source="VRA Core Oversight Committee">
        <measurementsSet>
            <display></display>
            <notes/>
            <measurements/>
        </measurementsSet>
        <relationSet>
            <relation></relation>
        </relationSet>
        <rightsSet>
            <display>This Rights Statement is intended for use with an Item that has been identified as in copyright but for which no rights-holder(s) has been identified or located after some reasonable investigation. This Rights Statement should only be used if the data provider is reasonably sure that the work is in copyright. This Rights Statement is not intended for use by EU-based data providers who have identified works as Orphan Works in accordance with the EU Orphan Works Directive (they must use InC-OW-EU instead).
                URI: http://rightsstatements.org/vocab/InC-RUU/1.0/</display>
            <rights/>
        </rightsSet>
        <sourceSet>
            <display>https://www.getty.edu/research/exhibitions_events/events/minimalism/index.html</display>
            <source>
                <name/>
                <refid></refid>
            </source>
        </sourceSet>
        <titleSet>
            <display></display>
            <title type="creator">Larry Bell</title>
        </titleSet>
        <worktypeSet>
            <display>glass sculpture</display>
            <notes/>
            <worktype/>
        </worktypeSet>
    </image>
    </vraSection>
    
    <dcSection>
        <dc:subject>Minimalist Art</dc:subject>
        <dc:description>Larry Bell became interested in glass in the early 1960s. As a medium, it had three properties that interested: it could transmit, absorb and reflect light, and with specific treatment, it could do all three at the same time. He found the cube to be an ideal form with which to investigate the phenomena of light on surface. The first cubes were made using household mirrors from which he would scratch away parts of the reflective material. Later he discovered a plating process that would make the glass reflective on both sides. With the early cubes, he incorporated geometric imagery, including the ellipse, adding visual complexity and depth to the simple forms. Eventually he eliminated the imagery. With a technology that deposited exquisitely thin films of various metallic and non-metallic substances to the glass. The resulting visual spectrum of colors is in fact light reflected in different wavelengths off the surface of the glass. Bell has continued to revisit the cubes throughout his career.</dc:description>
        <dc:date>1963</dc:date>
        <dc:identifier>2014.1.090</dc:identifier>
        <dc:coverage>20th century</dc:coverage>
        
    </dcSection>
    
    
    
    
    
    
</minimalist>

